config_files/config.yml
config_files/config_test.yml
docker/Dockerfile_ubuntu_18.04
docs/.nojekyll
docs/Makefile
docs/build/.buildinfo
docs/build/api.html
docs/build/genindex.html
docs/build/index.html
docs/build/modules.html
docs/build/objects.inv
docs/build/py-modindex.html
docs/build/readme_link.html
docs/build/search.html
docs/build/searchindex.js
docs/build/summit.examples.html
docs/build/summit.html
docs/build/summit.multiview_platform.html
docs/build/summit.multiview_platform.metrics.html
docs/build/summit.multiview_platform.monoview.html
docs/build/summit.multiview_platform.monoview_classifiers.additions.html
docs/build/summit.multiview_platform.monoview_classifiers.html
docs/build/summit.multiview_platform.multiview.html
docs/build/summit.multiview_platform.multiview_classifiers.additions.html
docs/build/summit.multiview_platform.multiview_classifiers.html
docs/build/summit.multiview_platform.result_analysis.html
docs/build/summit.multiview_platform.utils.html
docs/build/summit.tests.html
docs/build/summit.tests.test_metrics.html
docs/build/summit.tests.test_mono_view.html
docs/build/summit.tests.test_monoview_classifiers.html
docs/build/summit.tests.test_multi_view.html
docs/build/summit.tests.test_multiview_classifiers.Test_PseudoCQMeasure.html
docs/build/summit.tests.test_multiview_classifiers.html
docs/build/summit.tests.test_multiview_classifiers.test_additions.html
docs/build/summit.tests.test_result_analysis.html
docs/build/summit.tests.test_utils.html
docs/build/.doctrees/api.doctree
docs/build/.doctrees/environment.pickle
docs/build/.doctrees/index.doctree
docs/build/.doctrees/modules.doctree
docs/build/.doctrees/readme_link.doctree
docs/build/.doctrees/summit.doctree
docs/build/.doctrees/summit.examples.doctree
docs/build/.doctrees/summit.multiview_platform.doctree
docs/build/.doctrees/summit.multiview_platform.metrics.doctree
docs/build/.doctrees/summit.multiview_platform.monoview.doctree
summit_multi_learn-0.0.2.dist-info/METADATA
summit_multi_learn-0.0.2.dist-info/WHEEL
summit_multi_learn-0.0.2.dist-info/top_level.txt
summit_multi_learn-0.0.2.dist-info/RECORD
