Metadata-Version: 2.4
Name: summit-multi-learn
Version: 0.0.2
Summary: Supervised MultiModal Integration Tool
Author-email: Baptiste Bauvin <baptiste.bauvin.work@gmail.com>
License: BSD-3-Clause
Project-URL: Sources, https://github.com/multi-learn/summit
Project-URL: Documentation, https://multi-learn.github.io/summit/
Project-URL: Bug Tracker, https://github.com/multi-learn/summit/issues
Keywords: machine learning, supervised learning, classification, tool, multiview learning, monoview learning
Classifier: Development Status :: 5 - Production/Stable
Classifier: Intended Audience :: Science/Research
Classifier: Programming Language :: Python :: 3
Classifier: Programming Language :: Python :: 3.6
Classifier: Programming Language :: Python :: 3.7
Classifier: Programming Language :: Python :: 3.8
Classifier: Programming Language :: Python :: 3.9
Classifier: Programming Language :: Python :: 3.10
Classifier: Programming Language :: Python :: 3.11
Classifier: Programming Language :: Python :: 3.12
Classifier: Topic :: Scientific/Engineering
Classifier: Topic :: Scientific/Engineering :: Artificial Intelligence
Classifier: Operating System :: Microsoft :: Windows
Classifier: Operating System :: POSIX :: Linux
Classifier: Operating System :: MacOS :: MacOS X
Requires-Python: >=3.6
Requires-Dist: h5py>=2.9.0
Requires-Dist: joblib>=0.13.2
Requires-Dist: numpy>=1.24.0
Requires-Dist: pyparsing>=2.4.0
Requires-Dist: python-dateutil>=2.8.0
Requires-Dist: scikit-learn>=1.2.1
Requires-Dist: scipy>=1.3.0
Requires-Dist: six>=1.12.0
Requires-Dist: pandas>=0.23.3
Requires-Dist: pyyaml>=3.12
Requires-Dist: plotly>=4.2.1
Requires-Dist: matplotlib>=3.1.1
Requires-Dist: tabulate>=0.8.6
Requires-Dist: pyscm-ml>=1.0.0
Requires-Dist: imbalanced-learn>=0.10.1
Requires-Dist: scikit-multimodallearn>=0.1.0
Requires-Dist: randomscm==0.1.2
Provides-Extra: test
Requires-Dist: pytest; extra == "test"
Requires-Dist: pytest-cov; extra == "test"
Provides-Extra: doc
Requires-Dist: sphinx>=3.0.2; extra == "doc"
Requires-Dist: numpydoc; extra == "doc"
Requires-Dist: docutils; extra == "doc"
Requires-Dist: sphinx-autoapi; extra == "doc"
Requires-Dist: sphinx_rtd_theme; extra == "doc"
Dynamic: license
